bearblog_mcp/__init__.py
bearblog_mcp/__main__.py
bearblog_mcp/client.py
bearblog_mcp/server.py
bearblog_mcp_server-0.1.1.dist-info/licenses/LICENSE
bearblog_mcp_server-0.1.1.dist-info/METADATA
bearblog_mcp_server-0.1.1.dist-info/WHEEL
bearblog_mcp_server-0.1.1.dist-info/entry_points.txt
bearblog_mcp_server-0.1.1.dist-info/top_level.txt
bearblog_mcp_server-0.1.1.dist-info/RECORD
