Metadata-Version: 2.4
Name: bearblog-mcp-server
Version: 0.1.1
Summary: MCP server for Bear Blog integration
Author-email: Rocky Munoz <almostheresy@gmail.com>
License: MIT
Project-URL: Homepage, https://github.com/rockymunoz/bearblog-mcp-server
Project-URL: Repository, https://github.com/rockymunoz/bearblog-mcp-server
Keywords: mcp,bearblog,blog,model-context-protocol,claude,ai
Classifier: Development Status :: 4 - Beta
Classifier: Intended Audience :: Developers
Classifier: License :: OSI Approved :: MIT License
Classifier: Programming Language :: Python :: 3
Classifier: Programming Language :: Python :: 3.10
Classifier: Programming Language :: Python :: 3.11
Classifier: Programming Language :: Python :: 3.12
Classifier: Topic :: Software Development :: Libraries :: Python Modules
Classifier: Topic :: Internet :: WWW/HTTP :: Dynamic Content :: Content Management System
Requires-Python: >=3.10
License-File: LICENSE
Requires-Dist: fastmcp>=2.0.0
Requires-Dist: requests>=2.31.0
Requires-Dist: python-dotenv>=1.0.0
Provides-Extra: dev
Requires-Dist: pytest>=7.4.0; extra == "dev"
Requires-Dist: black>=23.0.0; extra == "dev"
Requires-Dist: ruff>=0.1.0; extra == "dev"
Dynamic: license-file
